sitecrawl/__init__.py
sitecrawl/__main__.py
sitecrawl/crawl.py
sitecrawl-1.0.5.dist-info/LICENSE
sitecrawl-1.0.5.dist-info/METADATA
sitecrawl-1.0.5.dist-info/WHEEL
sitecrawl-1.0.5.dist-info/entry_points.txt
sitecrawl-1.0.5.dist-info/top_level.txt
sitecrawl-1.0.5.dist-info/RECORD
