Metadata-Version: 2.1
Name: sitecrawl
Version: 1.0.5
Summary: Simple Python3 module to crawl a website and extract URLs
Home-page: https://github.com/gabfl/sitecrawl
Author: Gabriel Bordeaux
Author-email: pypi@gab.lc
License: MIT
Platform: UNKNOWN
Classifier: Topic :: Internet
Classifier: Topic :: Internet :: WWW/HTTP :: Site Management :: Link Checking
Classifier: Topic :: Software Development :: Libraries
Classifier: Topic :: Software Development
Classifier: License :: OSI Approved :: MIT License
Classifier: Operating System :: MacOS
Classifier: Operating System :: POSIX :: Linux
Classifier: Natural Language :: English
Classifier: Programming Language :: Python :: 3
Classifier: Programming Language :: Python
Classifier: Development Status :: 4 - Beta
Requires-Dist: requests
Requires-Dist: bs4
